startrek/__init__.py
startrek/arrival.py
startrek/departure.py
startrek/dock.py
startrek/stardocker.py
startrek/stargate.py
startrek/fsm/__init__.py
startrek/fsm/auto.py
startrek/fsm/base.py
startrek/fsm/machine.py
startrek/net/__init__.py
startrek/net/channel.py
startrek/net/connection.py
startrek/net/delegate.py
startrek/net/hub.py
startrek/net/socket.py
startrek/net/state.py
startrek/port/__init__.py
startrek/port/delegate.py
startrek/port/docker.py
startrek/port/gate.py
startrek/port/ship.py
startrek/skywalker/__init__.py
startrek/skywalker/daemon.py
startrek/skywalker/runner.py
startrek/skywalker/ticker.py
startrek/socket/__init__.py
startrek/socket/active_conn.py
startrek/socket/base_channel.py
startrek/socket/base_conn.py
startrek/socket/base_hub.py
startrek/types/__init__.py
startrek/types/mapping.py
startrek/types/pair.py
startrek-2.2.2.dist-info/METADATA
startrek-2.2.2.dist-info/WHEEL
startrek-2.2.2.dist-info/top_level.txt
startrek-2.2.2.dist-info/RECORD
